    <w:p w14:paraId="189E686C" w14:textId="77777777" w:rsidR="00D67F70" w:rsidRPr="004B2EA5" w:rsidRDefault="00D67F70" w:rsidP="00D67F70">
      <w:pPr>
        <w:autoSpaceDE w:val="0"/>
        <w:autoSpaceDN w:val="0"/>
        <w:adjustRightInd w:val="0"/>
        <w:spacing w:after="0" w:line="220" w:lineRule="atLeast"/>
        <w:ind w:left="113" w:hanging="113"/>
        <w:jc w:val="both"/>
        <w:textAlignment w:val="center"/>
        <w:rPr>
          <w:rFonts w:ascii="Times New Roman" w:hAnsi="Times New Roman"/>
          <w:color w:val="000000"/>
          <w:sz w:val="16"/>
          <w:szCs w:val="16"/>
        </w:rPr>
      </w:pPr>
      <w:r w:rsidRPr="004B2EA5">
        <w:rPr>
          <w:rFonts w:ascii="Times New Roman" w:hAnsi="Times New Roman"/>
          <w:b/>
          <w:bCs/>
          <w:color w:val="000000"/>
          <w:sz w:val="16"/>
          <w:szCs w:val="16"/>
        </w:rPr>
        <w:t>Ultuna</w:t>
      </w:r>
      <w:r w:rsidRPr="004B2EA5">
        <w:rPr>
          <w:rFonts w:ascii="Times New Roman" w:hAnsi="Times New Roman"/>
          <w:color w:val="000000"/>
          <w:sz w:val="16"/>
          <w:szCs w:val="16"/>
        </w:rPr>
        <w:t> </w:t>
      </w:r>
      <w:r w:rsidRPr="004B2EA5">
        <w:rPr>
          <w:rFonts w:ascii="Times New Roman" w:hAnsi="Times New Roman"/>
          <w:color w:val="000000"/>
          <w:sz w:val="16"/>
          <w:szCs w:val="16"/>
        </w:rPr>
        <w:t>Sveriges lantbruksuniversitet, f.d. gods, Uppsala stad, Uppland. (</w:t>
      </w:r>
      <w:r w:rsidRPr="004B2EA5">
        <w:rPr>
          <w:rFonts w:ascii="Times New Roman" w:hAnsi="Times New Roman"/>
          <w:i/>
          <w:iCs/>
          <w:color w:val="000000"/>
          <w:sz w:val="16"/>
          <w:szCs w:val="16"/>
        </w:rPr>
        <w:t>in</w:t>
      </w:r>
      <w:r w:rsidRPr="004B2EA5">
        <w:rPr>
          <w:rFonts w:ascii="Times New Roman" w:hAnsi="Times New Roman"/>
          <w:color w:val="000000"/>
          <w:sz w:val="16"/>
          <w:szCs w:val="16"/>
        </w:rPr>
        <w:t xml:space="preserve">) </w:t>
      </w:r>
      <w:r w:rsidRPr="004B2EA5">
        <w:rPr>
          <w:rFonts w:ascii="Times New Roman" w:hAnsi="Times New Roman"/>
          <w:i/>
          <w:iCs/>
          <w:color w:val="000000"/>
          <w:sz w:val="16"/>
          <w:szCs w:val="16"/>
        </w:rPr>
        <w:t>villa Wlertune</w:t>
      </w:r>
      <w:r w:rsidRPr="004B2EA5">
        <w:rPr>
          <w:rFonts w:ascii="Times New Roman" w:hAnsi="Times New Roman"/>
          <w:color w:val="000000"/>
          <w:sz w:val="16"/>
          <w:szCs w:val="16"/>
        </w:rPr>
        <w:t xml:space="preserve"> 1221. – Namnet innehåller genitiv av gudanamnet </w:t>
      </w:r>
      <w:r w:rsidRPr="004B2EA5">
        <w:rPr>
          <w:rFonts w:ascii="Times New Roman" w:hAnsi="Times New Roman"/>
          <w:i/>
          <w:iCs/>
          <w:color w:val="000000"/>
          <w:sz w:val="16"/>
          <w:szCs w:val="16"/>
        </w:rPr>
        <w:t>Ull</w:t>
      </w:r>
      <w:r w:rsidRPr="004B2EA5">
        <w:rPr>
          <w:rFonts w:ascii="Times New Roman" w:hAnsi="Times New Roman"/>
          <w:color w:val="000000"/>
          <w:sz w:val="16"/>
          <w:szCs w:val="16"/>
        </w:rPr>
        <w:t xml:space="preserve"> och </w:t>
      </w:r>
      <w:r w:rsidR="008341E4" w:rsidRPr="004B2EA5">
        <w:rPr>
          <w:rFonts w:ascii="Times New Roman" w:hAnsi="Times New Roman"/>
          <w:color w:val="000000"/>
          <w:sz w:val="16"/>
          <w:szCs w:val="16"/>
        </w:rPr>
        <w:t>→</w:t>
      </w:r>
      <w:r w:rsidRPr="004B2EA5">
        <w:rPr>
          <w:rFonts w:ascii="Times New Roman" w:hAnsi="Times New Roman"/>
          <w:color w:val="000000"/>
          <w:sz w:val="16"/>
          <w:szCs w:val="16"/>
        </w:rPr>
        <w:t xml:space="preserve"> </w:t>
      </w:r>
      <w:r w:rsidRPr="004B2EA5">
        <w:rPr>
          <w:rFonts w:ascii="Times New Roman" w:hAnsi="Times New Roman"/>
          <w:i/>
          <w:iCs/>
          <w:color w:val="000000"/>
          <w:sz w:val="16"/>
          <w:szCs w:val="16"/>
        </w:rPr>
        <w:t>tuna</w:t>
      </w:r>
      <w:r w:rsidRPr="004B2EA5">
        <w:rPr>
          <w:rFonts w:ascii="Times New Roman" w:hAnsi="Times New Roman"/>
          <w:color w:val="000000"/>
          <w:sz w:val="16"/>
          <w:szCs w:val="16"/>
        </w:rPr>
        <w:t xml:space="preserve">. Gudanamnet ingår också i häradsnamnet </w:t>
      </w:r>
      <w:r w:rsidRPr="004B2EA5">
        <w:rPr>
          <w:rFonts w:ascii="Times New Roman" w:hAnsi="Times New Roman"/>
          <w:i/>
          <w:iCs/>
          <w:color w:val="000000"/>
          <w:sz w:val="16"/>
          <w:szCs w:val="16"/>
        </w:rPr>
        <w:t>Ulleråkers härad</w:t>
      </w:r>
      <w:r w:rsidRPr="004B2EA5">
        <w:rPr>
          <w:rFonts w:ascii="Times New Roman" w:hAnsi="Times New Roman"/>
          <w:color w:val="000000"/>
          <w:sz w:val="16"/>
          <w:szCs w:val="16"/>
        </w:rPr>
        <w:t xml:space="preserve">. Relationen mellan de båda namnen är omdiskuterad. Se vidare </w:t>
      </w:r>
      <w:r w:rsidR="008341E4" w:rsidRPr="004B2EA5">
        <w:rPr>
          <w:rFonts w:ascii="Times New Roman" w:hAnsi="Times New Roman"/>
          <w:color w:val="000000"/>
          <w:sz w:val="16"/>
          <w:szCs w:val="16"/>
        </w:rPr>
        <w:t>→</w:t>
      </w:r>
      <w:r w:rsidRPr="004B2EA5">
        <w:rPr>
          <w:rFonts w:ascii="Times New Roman" w:hAnsi="Times New Roman"/>
          <w:color w:val="000000"/>
          <w:sz w:val="16"/>
          <w:szCs w:val="16"/>
        </w:rPr>
        <w:t xml:space="preserve"> </w:t>
      </w:r>
      <w:r w:rsidRPr="004B2EA5">
        <w:rPr>
          <w:rFonts w:ascii="Times New Roman" w:hAnsi="Times New Roman"/>
          <w:i/>
          <w:iCs/>
          <w:color w:val="000000"/>
          <w:sz w:val="16"/>
          <w:szCs w:val="16"/>
        </w:rPr>
        <w:t>Ulleråkers härad</w:t>
      </w:r>
      <w:r w:rsidRPr="004B2EA5">
        <w:rPr>
          <w:rFonts w:ascii="Times New Roman" w:hAnsi="Times New Roman"/>
          <w:color w:val="000000"/>
          <w:sz w:val="16"/>
          <w:szCs w:val="16"/>
        </w:rPr>
        <w:t>.</w:t>
      </w:r>
    </w:p>
